<?xml version = '1.0' encoding = 'UTF-8'?>
<Diagram class="oracle.dbtools.crest.swingui.logical.DPVLogical" name="Logical" id="DB9BC939-1E69-933C-D908-5335C838A026">
<createdBy>S6N0C</createdBy>
<modifiedBy>S6N0C</modifiedBy>
<createdTime>2025-06-20 01:27:02 UTC</createdTime>
<autoRoute>false</autoRoute>
<boxInbox>true</boxInbox>
<showLegend>false</showLegend>
<showLabels>false</showLabels>
<showRelAttributes>false</showRelAttributes>
<gridEnabled>false</gridEnabled>
<showGrid>false</showGrid>
<diagramColor>-1</diagramColor>
<display>false</display>
<notation>1</notation>
<objectViews>
<OView class="oracle.dbtools.crest.swingui.logical.TVEntity" oid="F2BDA191-9FB1-FF9D-C889-8AF840BB5ECF" otype="Entity" vid="90F39AE5-3011-D6CC-2082-111237EBFAB3">
<hideElementsInCurrentOnly>false</hideElementsInCurrentOnly>
<bounds x="221" y="163" width="170" height="110"/>
</OView>
</objectViews>
</Diagram>